{"code":0,"message":"0","ttl":1,"data":{"cursor":{"all_count":105,"is_begin":false,"prev":4,"next":5,"is_end":false,"mode":3,"show_type":1,"support_mode":[1,2,3],"name":"热门评论"},"hots":null,"notice":null,"replies":[{"rpid":1300430624,"oid":1858957,"type":12,"mid":260484890,"root":0,"parent":0,"dialog":0,"count":0,"rcount":0,"state":0,"fansgrade":0,"attr":0,"ctime":1547351720,"rpid_str":"1300430624","root_str":"0","parent_str":"0","like":1,"action":0,"member":{"mid":"260484890","uname":"gffvhn","sex":"保密","sign":"moyoharu天下第一!","avatar":"http://i2.hdslb.com/bfs/face/cab5f82fc86a9477369370e3f3ba7e1eceb95171.jpg","rank":"10000","DisplayRank":"0","face_nft_new":0,"is_senior_member":0,"level_info":{"current_level":5,"current_min":0,"current_exp":0,"next_exp":0},"pendant":{"pid":0,"name":"","image":"","expire":0,"image_enhance":"","image_enhance_frame":""},"nameplate":{"nid":0,"name":"","image":"","image_small":"","level":"","condition":""},"official_verify":{"type":-1,"desc":""},"vip":{"vipType":1,"vipDueDate":1642003200000,"dueRemark":"","accessStatus":0,"vipStatus":0,"vipStatusWarn":"","themeType":0,"label":{"path":"","text":"","label_theme":"","text_color":"","bg_style":0,"bg_color":"","border_color":""},"avatar_subscript":0,"nickname_color":""},"fans_detail":null,"following":0,"is_followed":0,"user_sailing":{"pendant":null,"cardbg":null,"cardbg_with_focus":null},"is_contractor":false,"contract_desc":""},"content":{"message":"团宠三岁光","plat":0,"device":"","members":[],"jump_url":{},"max_line":6},"replies":null,"assist":0,"folder":{"has_folded":false,"is_folded":false,"rule":"https://www.bilibili.com/blackboard/foldingreply.html"},"up_action":{"like":false,"reply":false},"show_follow":false,"invisible":false,"reply_control":{"time_desc":"1099天前发布"}},{"rpid":1300405626,"oid":1858957,"type":12,"mid":1879254,"root":0,"parent":0,"dialog":0,"count":0,"rcount":0,"state":0,"fansgrade":0,"attr":0,"ctime":1547350933,"rpid_str":"1300405626","root_str":"0","parent_str":"0","like":1,"action":0,"member":{"mid":"1879254","uname":"帕瓦双子","sex":"保密","sign":"在异性中看见爱，在百合花中看见天堂——鲁迅《尘影》题辞","avatar":"http://i0.hdslb.com/bfs/face/9e96584e97214bfe360bf9f781c0307e5f7f48c9.jpg","rank":"10000","DisplayRank":"0","face_nft_new":0,"is_senior_member":0,"level_info":{"current_level":6,"current_min":0,"current_exp":0,"next_exp":0},"pendant":{"pid":0,"name":"","image":"","expire":0,"image_enhance":"","image_enhance_frame":""},"nameplate":{"nid":8,"name":"知名偶像","image":"http://i2.hdslb.com/bfs/face/27a952195555e64508310e366b3e38bd4cd143fc.png","image_small":"http://i1.hdslb.com/bfs/face/0497be49e08357bf05bca56e33a0637a273a7610.png","level":"稀有勋章","condition":"所有自制视频总播放数>=100万"},"official_verify":{"type":-1,"desc":""},"vip":{"vipType":1,"vipDueDate":1634745600000,"dueRemark":"","accessStatus":0,"vipStatus":0,"vipStatusWarn":"","themeType":0,"label":{"path":"","text":"","label_theme":"","text_color":"","bg_style":0,"bg_color":"","border_color":""},"avatar_subscript":0,"nickname_color":""},"fans_detail":null,"following":0,"is_followed":0,"user_sailing":{"pendant":null,"cardbg":null,"cardbg_with_focus":null},"is_contractor":false,"contract_desc":""},"content":{"message":"好甜，好暖","plat":0,"device":"","members":[],"jump_url":{},"max_line":6},"replies":null,"assist":0,"folder":{"has_folded":false,"is_folded":false,"rule":"https://www.bilibili.com/blackboard/foldingreply.html"},"up_action":{"like":false,"reply":false},"show_follow":false,"invisible":false,"reply_control":{"time_desc":"1099天前发布"}},{"rpid":1300398781,"oid":1858957,"type":12,"mid":234425,"root":0,"parent":0,"dialog":0,"count":0,"rcount":0,"state":0,"fansgrade":0,"attr":0,"ctime":1547351480,"rpid_str":"1300398781","root_str":"0","parent_str":"0","like":1,"action":0,"member":{"mid":"234425","uname":"RainLove804","sex":"保密","sign":"","avatar":"http://i2.hdslb.com/bfs/face/9bc3a0f3612c1b5a411352082be8b44a95725c1d.jpg","rank":"10000","DisplayRank":"0","face_nft_new":0,"is_senior_member":0,"level_info":{"current_level":5,"current_min":0,"current_exp":0,"next_exp":0},"pendant":{"pid":0,"name":"","image":"","expire":0,"image_enhance":"","image_enhance_frame":""},"nameplate":{"nid":0,"name":"","image":"","image_small":"","level":"","condition":""},"official_verify":{"type":-1,"desc":""},"vip":{"vipType":2,"vipDueDate":1681488000000,"dueRemark":"","accessStatus":0,"vipStatus":1,"vipStatusWarn":"","themeType":0,"label":{"path":"","text":"年度大会员","label_theme":"annual_vip","text_color":"#FFFFFF","bg_style":1,"bg_color":"#FB7299","border_color":""},"avatar_subscript":1,"avatar_subscript_url":"http://i0.hdslb.com/bfs/vip/icon_Certification_big_member_22_3x.png","nickname_color":"#FB7299"},"fans_detail":null,"following":0,"is_followed":0,"user_sailing":{"pendant":null,"cardbg":null,"cardbg_with_focus":null},"is_contractor":false,"contract_desc":""},"content":{"message":"看到金拱门，我就笑死了","plat":0,"device":"","members":[],"jump_url":{},"max_line":6},"replies":null,"assist":0,"folder":{"has_folded":false,"is_folded":false,"rule":"https://www.bilibili.com/blackboard/foldingreply.html"},"up_action":{"like":false,"reply":false},"show_follow":false,"invisible":false,"reply_control":{"time_desc":"1099天前发布"}},{"rpid":1300373361,"oid":1858957,"type":12,"mid":13112055,"root":0,"parent":0,"dialog":0,"count":0,"rcount":0,"state":0,"fansgrade":0,"attr":0,"ctime":1547350143,"rpid_str":"1300373361","root_str":"0","parent_str":"0","like":1,"action":0,"member":{"mid":"13112055","uname":"Sananthachat","sex":"女","sign":"现实中就我一个沉迷二次元，还是沙雕网友温暖人心。","avatar":"http://i0.hdslb.com/bfs/face/9f251c2861f3185726835db6c51c0c21cdda8833.jpg","rank":"10000","DisplayRank":"0","face_nft_new":0,"is_senior_member":0,"level_info":{"current_level":5,"current_min":0,"current_exp":0,"next_exp":0},"pendant":{"pid":0,"name":"","image":"","expire":0,"image_enhance":"","image_enhance_frame":""},"nameplate":{"nid":36,"name":"终身卡","image":"http://i2.hdslb.com/bfs/face/3599502e13044295e43a44ae44bb19cae7d0514a.png","image_small":"http://i2.hdslb.com/bfs/face/6e2c3d68fcb89af046f2669cd0acfa5df55aa029.png","level":"稀有勋章","condition":"直播用户等级>=40级"},"official_verify":{"type":-1,"desc":""},"vip":{"vipType":0,"vipDueDate":0,"dueRemark":"","accessStatus":0,"vipStatus":0,"vipStatusWarn":"","themeType":0,"label":{"path":"","text":"","label_theme":"","text_color":"","bg_style":0,"bg_color":"","border_color":""},"avatar_subscript":0,"nickname_color":""},"fans_detail":null,"following":0,"is_followed":0,"user_sailing":{"pendant":null,"cardbg":null,"cardbg_with_focus":null},"is_contractor":false,"contract_desc":""},"content":{"message":"小光团宠无疑！","plat":0,"device":"","members":[],"jump_url":{},"max_line":6},"replies":null,"assist":0,"folder":{"has_folded":false,"is_folded":false,"rule":"https://www.bilibili.com/blackboard/foldingreply.html"},"up_action":{"like":false,"reply":false},"show_follow":false,"invisible":false,"reply_control":{"time_desc":"1099天前发布"}},{"rpid":1300081869,"oid":1858957,"type":12,"mid":3735503,"root":0,"parent":0,"dialog":0,"count":0,"rcount":0,"state":0,"fansgrade":1,"attr":0,"ctime":1547339918,"rpid_str":"1300081869","root_str":"0","parent_str":"0","like":1,"action":0,"member":{"mid":"3735503","uname":"最后的死尸","sex":"保密","sign":"","avatar":"http://i2.hdslb.com/bfs/face/b53bfcaafde3c96439a9edd3179aaf914a6f4269.jpg","rank":"10000","DisplayRank":"0","face_nft_new":0,"is_senior_member":0,"level_info":{"current_level":6,"current_min":0,"current_exp":0,"next_exp":0},"pendant":{"pid":0,"name":"","image":"","expire":0,"image_enhance":"","image_enhance_frame":""},"nameplate":{"nid":57,"name":"收集萌新","image":"http://i1.hdslb.com/bfs/face/7767275600ea63d351b22fa87ec15a79aa24e5e5.png","image_small":"http://i2.hdslb.com/bfs/face/6589d992655595bf51543f268040eaeaed372fae.png","level":"普通勋章","condition":"同时拥有粉丝勋章>=5个"},"official_verify":{"type":-1,"desc":""},"vip":{"vipType":1,"vipDueDate":1627660800000,"dueRemark":"","accessStatus":0,"vipStatus":0,"vipStatusWarn":"","themeType":0,"label":{"path":"","text":"","label_theme":"","text_color":"","bg_style":0,"bg_color":"","border_color":""},"avatar_subscript":0,"nickname_color":""},"fans_detail":{"uid":3735503,"medal_id":126450,"medal_name":"创造科","score":0,"level":1,"intimacy":0,"master_status":1,"is_receive":1,"medal_color":643602062,"medal_color_end":643602062,"medal_color_border":4284257934,"medal_color_name":4284257934,"medal_color_level":4284257934,"guard_level":0},"following":0,"is_followed":0,"user_sailing":{"pendant":null,"cardbg":null,"cardbg_with_focus":null},"is_contractor":false,"contract_desc":""},"content":{"message":"四格真是欢乐之源","plat":0,"device":"","members":[],"jump_url":{},"max_line":6},"replies":null,"assist":0,"folder":{"has_folded":false,"is_folded":false,"rule":"https://www.bilibili.com/blackboard/foldingreply.html"},"up_action":{"like":false,"reply":false},"show_follow":false,"invisible":false,"reply_control":{"time_desc":"1099天前发布"}},{"rpid":1300021273,"oid":1858957,"type":12,"mid":4971531,"root":0,"parent":0,"dialog":0,"count":0,"rcount":0,"state":0,"fansgrade":0,"attr":0,"ctime":1547335741,"rpid_str":"1300021273","root_str":"0","parent_str":"0","like":1,"action":0,"member":{"mid":"4971531","uname":"环妈妈","sex":"女","sign":"世上还有比百合更美的事物吗\n猫鳥は人類の光である","avatar":"http://i0.hdslb.com/bfs/face/fce7a4eb7983f650c96b33b01a8247ce0449ef2f.jpg","rank":"10000","DisplayRank":"0","face_nft_new":0,"is_senior_member":0,"level_info":{"current_level":6,"current_min":0,"current_exp":0,"next_exp":0},"pendant":{"pid":0,"name":"","image":"","expire":0,"image_enhance":"","image_enhance_frame":""},"nameplate":{"nid":59,"name":"大收藏家","image":"http://i0.hdslb.com/bfs/face/d12b5db77341e3285f25cc0db82f73e5681a0190.png","image_small":"http://i2.hdslb.com/bfs/face/6bd23ec2d295a5a3e3a8cdde107f62605fd4f9b7.png","level":"普通勋章","condition":"同时拥有粉丝勋章>=25个"},"official_verify":{"type":-1,"desc":""},"vip":{"vipType":2,"vipDueDate":1664467200000,"dueRemark":"","accessStatus":0,"vipStatus":1,"vipStatusWarn":"","themeType":0,"label":{"path":"","text":"年度大会员","label_theme":"annual_vip","text_color":"#FFFFFF","bg_style":1,"bg_color":"#FB7299","border_color":""},"avatar_subscript":1,"avatar_subscript_url":"http://i0.hdslb.com/bfs/vip/icon_Certification_big_member_22_3x.png","nickname_color":"#FB7299"},"fans_detail":null,"following":0,"is_followed":0,"user_sailing":{"pendant":null,"cardbg":null,"cardbg_with_focus":null},"is_contractor":false,"contract_desc":""},"content":{"message":"昼妈妈真是太好惹[2233娘_大笑]","plat":0,"device":"","members":[],"emote":{"[2233娘_大笑]":{"id":136,"package_id":6,"state":0,"type":2,"attr":0,"text":"[2233娘_大笑]","url":"http://i0.hdslb.com/bfs/emote/16b8794be990cefa6caeba4d901b934a227ee3b8.png","meta":{"size":2},"mtime":1626664892,"jump_title":"大笑"}},"jump_url":{},"max_line":6},"replies":null,"assist":0,"folder":{"has_folded":false,"is_folded":false,"rule":"https://www.bilibili.com/blackboard/foldingreply.html"},"up_action":{"like":false,"reply":false},"show_follow":false,"invisible":false,"reply_control":{"time_desc":"1099天前发布"}},{"rpid":1299932378,"oid":1858957,"type":12,"mid":333608,"root":0,"parent":0,"dialog":0,"count":0,"rcount":0,"state":0,"fansgrade":0,"attr":0,"ctime":1547323627,"rpid_str":"1299932378","root_str":"0","parent_str":"0","like":1,"action":0,"member":{"mid":"333608","uname":"yuritopia544","sex":"保密","sign":"おお雕を食べいましょか？","avatar":"http://i2.hdslb.com/bfs/face/af196c66a8519fa00bc979fea0c28cfee08b87b3.gif","rank":"10000","DisplayRank":"0","face_nft_new":0,"is_senior_member":0,"level_info":{"current_level":5,"current_min":0,"current_exp":0,"next_exp":0},"pendant":{"pid":0,"name":"","image":"","expire":0,"image_enhance":"","image_enhance_frame":""},"nameplate":{"nid":0,"name":"","image":"","image_small":"","level":"","condition":""},"official_verify":{"type":-1,"desc":""},"vip":{"vipType":1,"vipDueDate":1574611200000,"dueRemark":"","accessStatus":0,"vipStatus":0,"vipStatusWarn":"","themeType":0,"label":{"path":"","text":"","label_theme":"","text_color":"","bg_style":0,"bg_color":"","border_color":""},"avatar_subscript":0,"nickname_color":""},"fans_detail":null,"following":0,"is_followed":0,"user_sailing":{"pendant":null,"cardbg":null,"cardbg_with_focus":null},"is_contractor":false,"contract_desc":""},"content":{"message":"是我最喜欢的四格，这个快些动画化啊","plat":0,"device":"","members":[],"jump_url":{},"max_line":6},"replies":null,"assist":0,"folder":{"has_folded":false,"is_folded":false,"rule":"https://www.bilibili.com/blackboard/foldingreply.html"},"up_action":{"like":false,"reply":false},"show_follow":false,"invisible":false,"reply_control":{"time_desc":"1099天前发布"}},{"rpid":1303021380,"oid":1858957,"type":12,"mid":217756,"root":0,"parent":0,"dialog":0,"count":0,"rcount":0,"state":0,"fansgrade":0,"attr":0,"ctime":1547448072,"rpid_str":"1303021380","root_str":"0","parent_str":"0","like":2,"action":0,"member":{"mid":"217756","uname":"非典型小龙虾","sex":"女","sign":"","avatar":"http://i1.hdslb.com/bfs/face/0c796279b63221fc1831539b2e1cde8109237679.jpg","rank":"10000","DisplayRank":"0","face_nft_new":0,"is_senior_member":0,"level_info":{"current_level":6,"current_min":0,"current_exp":0,"next_exp":0},"pendant":{"pid":0,"name":"","image":"","expire":0,"image_enhance":"","image_enhance_frame":""},"nameplate":{"nid":0,"name":"","image":"","image_small":"","level":"","condition":""},"official_verify":{"type":-1,"desc":""},"vip":{"vipType":1,"vipDueDate":1625587200000,"dueRemark":"","accessStatus":0,"vipStatus":0,"vipStatusWarn":"","themeType":0,"label":{"path":"","text":"","label_theme":"","text_color":"","bg_style":0,"bg_color":"","border_color":""},"avatar_subscript":0,"nickname_color":""},"fans_detail":null,"following":0,"is_followed":0,"user_sailing":{"pendant":null,"cardbg":null,"cardbg_with_focus":null},"is_contractor":false,"contract_desc":""},"content":{"message":"真矢sama很能吃看来已经是大家公认的了(｡･ω･｡)","plat":0,"device":"","members":[],"jump_url":{},"max_line":6},"replies":null,"assist":0,"folder":{"has_folded":false,"is_folded":false,"rule":"https://www.bilibili.com/blackboard/foldingreply.html"},"up_action":{"like":false,"reply":false},"show_follow":false,"invisible":false,"reply_control":{"time_desc":"1098天前发布"}},{"rpid":1440959166,"oid":1858957,"type":12,"mid":33405840,"root":0,"parent":0,"dialog":0,"count":0,"rcount":0,"state":0,"fansgrade":0,"attr":0,"ctime":1552026665,"rpid_str":"1440959166","root_str":"0","parent_str":"0","like":0,"action":0,"member":{"mid":"33405840","uname":"馍馍馍馍er","sex":"男","sign":"阿巴阿巴玛卡巴卡","avatar":"http://i0.hdslb.com/bfs/face/6550d7bccc00332dd0aaa20809ffc57add83371e.jpg","rank":"10000","DisplayRank":"0","face_nft_new":0,"is_senior_member":0,"level_info":{"current_level":6,"current_min":0,"current_exp":0,"next_exp":0},"pendant":{"pid":0,"name":"","image":"","expire":0,"image_enhance":"","image_enhance_frame":""},"nameplate":{"nid":74,"name":"大会员2018年度勋章","image":"http://i0.hdslb.com/bfs/face/421179426c929dfeaed4117461c83f5d07ffb148.png","image_small":"http://i1.hdslb.com/bfs/face/682001c2e1c2ae887bdf2a0e18eef61180c48f84.png","level":"稀有勋章","condition":"2018.6.26-7.8某一天是年度大会员"},"official_verify":{"type":-1,"desc":""},"vip":{"vipType":2,"vipDueDate":1653062400000,"dueRemark":"","accessStatus":0,"vipStatus":1,"vipStatusWarn":"","themeType":0,"label":{"path":"","text":"年度大会员","label_theme":"annual_vip","text_color":"#FFFFFF","bg_style":1,"bg_color":"#FB7299","border_color":""},"avatar_subscript":1,"avatar_subscript_url":"http://i0.hdslb.com/bfs/vip/icon_Certification_big_member_22_3x.png","nickname_color":"#FB7299"},"fans_detail":null,"following":0,"is_followed":0,"user_sailing":{"pendant":null,"cardbg":null,"cardbg_with_focus":null},"is_contractor":false,"contract_desc":""},"content":{"message":"hrk之前再广播里说想演侦探角色（又是中之人逆输出加设定吗www","plat":0,"device":"","members":[],"jump_url":{},"max_line":6},"replies":null,"assist":0,"folder":{"has_folded":false,"is_folded":false,"rule":"https://www.bilibili.com/blackboard/foldingreply.html"},"up_action":{"like":false,"reply":false},"show_follow":false,"invisible":false,"reply_control":{"time_desc":"1045天前发布"}},{"rpid":1344215433,"oid":1858957,"type":12,"mid":2557429,"root":0,"parent":0,"dialog":0,"count":0,"rcount":0,"state":0,"fansgrade":0,"attr":0,"ctime":1548870858,"rpid_str":"1344215433","root_str":"0","parent_str":"0","like":0,"action":0,"member":{"mid":"2557429","uname":"抬頭仰望天空","sex":"女","sign":"▶不定期更ppp相关中字▶搬运伊藤彩沙ins限时动态▶頭像pixiv@curse3","avatar":"http://i1.hdslb.com/bfs/face/0972e0d515bff54cbf70e95f8862eac4d06a967b.jpg","rank":"10000","DisplayRank":"0","face_nft_new":0,"is_senior_member":0,"level_info":{"current_level":6,"current_min":0,"current_exp":0,"next_exp":0},"pendant":{"pid":0,"name":"","image":"","expire":0,"image_enhance":"","image_enhance_frame":""},"nameplate":{"nid":6,"name":"高级搬运工","image":"http://i2.hdslb.com/bfs/face/a9af39ab7ed08e078c45d58dd96a6411aba1a9d3.png","image_small":"http://i2.hdslb.com/bfs/face/46e5aae4667c72c379b46b51fac4b4426d9214e7.png","level":"高级勋章","condition":"转载视频投稿通过总数>=100"},"official_verify":{"type":-1,"desc":""},"vip":{"vipType":1,"vipDueDate":1518969600000,"dueRemark":"","accessStatus":0,"vipStatus":0,"vipStatusWarn":"","themeType":0,"label":{"path":"","text":"","label_theme":"","text_color":"","bg_style":0,"bg_color":"","border_color":""},"avatar_subscript":0,"nickname_color":""},"fans_detail":null,"following":0,"is_followed":0,"user_sailing":{"pendant":null,"cardbg":null,"cardbg_with_focus":null},"is_contractor":false,"contract_desc":""},"content":{"message":"前面看著很搞笑最後很暖啊…還有小光真的是太可愛了wwww","plat":0,"device":"","members":[],"jump_url":{},"max_line":6},"replies":null,"assist":0,"folder":{"has_folded":false,"is_folded":false,"rule":"https://www.bilibili.com/blackboard/foldingreply.html"},"up_action":{"like":false,"reply":false},"show_follow":false,"invisible":false,"reply_control":{"time_desc":"1081天前发布"}},{"rpid":1303056650,"oid":1858957,"type":12,"mid":10826451,"root":0,"parent":0,"dialog":0,"count":0,"rcount":0,"state":0,"fansgrade":0,"attr":0,"ctime":1547450002,"rpid_str":"1303056650","root_str":"0","parent_str":"0","like":0,"action":0,"member":{"mid":"10826451","uname":"纯亚_Junya","sex":"男","sign":"One word frees us of all the weight and pain of life.That is love","avatar":"http://i0.hdslb.com/bfs/face/fc0ea0888e541aa5ddc41a011a62b66a69f87781.jpg","rank":"10000","DisplayRank":"0","face_nft_new":0,"is_senior_member":0,"level_info":{"current_level":6,"current_min":0,"current_exp":0,"next_exp":0},"pendant":{"pid":4357,"name":"希萝Hiiro","image":"http://i0.hdslb.com/bfs/garb/item/afa6dc89047b1fc86a72996a4890d44871f8896e.png","expire":0,"image_enhance":"http://i0.hdslb.com/bfs/garb/item/afa6dc89047b1fc86a72996a4890d44871f8896e.png","image_enhance_frame":""},"nameplate":{"nid":38,"name":"学生卡","image":"http://i0.hdslb.com/bfs/face/21fdd1bcd9ad1b52d5725026d71c185a68681644.png","image_small":"http://i1.hdslb.com/bfs/face/250cf2b3d0ac2585d2176c0701075984f995df5c.png","level":"普通勋章","condition":"直播用户等级>=25级"},"official_verify":{"type":-1,"desc":""},"vip":{"vipType":2,"vipDueDate":1676131200000,"dueRemark":"","accessStatus":0,"vipStatus":1,"vipStatusWarn":"","themeType":0,"label":{"path":"","text":"年度大会员","label_theme":"annual_vip","text_color":"#FFFFFF","bg_style":1,"bg_color":"#FB7299","border_color":""},"avatar_subscript":1,"avatar_subscript_url":"http://i0.hdslb.com/bfs/vip/icon_Certification_big_member_22_3x.png","nickname_color":"#FB7299"},"fans_detail":null,"following":0,"is_followed":0,"user_sailing":{"pendant":{"id":4357,"name":"希萝Hiiro","image":"http://i0.hdslb.com/bfs/garb/item/afa6dc89047b1fc86a72996a4890d44871f8896e.png","jump_url":"","type":"suit","image_enhance":"http://i0.hdslb.com/bfs/garb/item/afa6dc89047b1fc86a72996a4890d44871f8896e.png","image_enhance_frame":""},"cardbg":{"id":4378,"name":"希萝Hiiro","image":"http://i0.hdslb.com/bfs/garb/item/780fe80e6dd77af4baa07d04952cb21e6b24ae66.png","jump_url":"https://www.bilibili.com/h5/mall/fans/recommend/4389?navhide=1&mid=10826451&from=reply","fan":{"is_fan":1,"number":6599,"color":"#ff7171","name":"希萝Hiiro","num_desc":"006599"},"type":"suit"},"cardbg_with_focus":null},"is_contractor":false,"contract_desc":""},"content":{"message":"闹钟露妈妈QAQ哭了","plat":0,"device":"","members":[],"jump_url":{},"max_line":6},"replies":null,"assist":0,"folder":{"has_folded":false,"is_folded":false,"rule":"https://www.bilibili.com/blackboard/foldingreply.html"},"up_action":{"like":false,"reply":false},"show_follow":false,"invisible":false,"reply_control":{"time_desc":"1098天前发布"}},{"rpid":1301967933,"oid":1858957,"type":12,"mid":298029510,"root":0,"parent":0,"dialog":0,"count":0,"rcount":0,"state":0,"fansgrade":0,"attr":0,"ctime":1547392567,"rpid_str":"1301967933","root_str":"0","parent_str":"0","like":0,"action":0,"member":{"mid":"298029510","uname":"活着终点是死亡","sex":"保密","sign":"","avatar":"http://i0.hdslb.com/bfs/face/058efc8e27717f9acb090684d6ce939a746a3ad6.jpg","rank":"10000","DisplayRank":"0","face_nft_new":0,"is_senior_member":0,"level_info":{"current_level":5,"current_min":0,"current_exp":0,"next_exp":0},"pendant":{"pid":4667,"name":"花丸晴琉","image":"http://i0.hdslb.com/bfs/garb/item/fbf375c8ab8ec5e8e01f2e775147a92752cd4d10.png","expire":0,"image_enhance":"http://i0.hdslb.com/bfs/garb/item/fbf375c8ab8ec5e8e01f2e775147a92752cd4d10.png","image_enhance_frame":""},"nameplate":{"nid":0,"name":"","image":"","image_small":"","level":"","condition":""},"official_verify":{"type":-1,"desc":""},"vip":{"vipType":2,"vipDueDate":1663776000000,"dueRemark":"","accessStatus":0,"vipStatus":1,"vipStatusWarn":"","themeType":0,"label":{"path":"","text":"年度大会员","label_theme":"annual_vip","text_color":"#FFFFFF","bg_style":1,"bg_color":"#FB7299","border_color":""},"avatar_subscript":1,"avatar_subscript_url":"http://i0.hdslb.com/bfs/vip/icon_Certification_big_member_22_3x.png","nickname_color":"#FB7299"},"fans_detail":null,"following":0,"is_followed":0,"user_sailing":{"pendant":{"id":4667,"name":"花丸晴琉","image":"http://i0.hdslb.com/bfs/garb/item/fbf375c8ab8ec5e8e01f2e775147a92752cd4d10.png","jump_url":"","type":"suit","image_enhance":"http://i0.hdslb.com/bfs/garb/item/fbf375c8ab8ec5e8e01f2e775147a92752cd4d10.png","image_enhance_frame":""},"cardbg":{"id":4693,"name":"花丸晴琉","image":"http://i0.hdslb.com/bfs/garb/item/8ea2762cb82283fc59f8053f9786c491e19bbab0.png","jump_url":"https://www.bilibili.com/h5/mall/fans/recommend/4696?navhide=1&mid=298029510&from=reply","fan":{"is_fan":1,"number":3812,"color":"#ffa356","name":"花丸晴琉","num_desc":"003812"},"type":"suit"},"cardbg_with_focus":null},"is_contractor":false,"contract_desc":""},"content":{"message":"不行，忍住不能笑","plat":0,"device":"","members":[],"jump_url":{},"max_line":6},"replies":null,"assist":0,"folder":{"has_folded":false,"is_folded":false,"rule":"https://www.bilibili.com/blackboard/foldingreply.html"},"up_action":{"like":false,"reply":false},"show_follow":false,"invisible":false,"reply_control":{"time_desc":"1098天前发布"}},{"rpid":1301793329,"oid":1858957,"type":12,"mid":225463,"root":0,"parent":0,"dialog":0,"count":0,"rcount":0,"state":0,"fansgrade":0,"attr":0,"ctime":1547388035,"rpid_str":"1301793329","root_str":"0","parent_str":"0","like":0,"action":0,"member":{"mid":"225463","uname":"阿尔伯特","sex":"男","sign":"Kya----","avatar":"http://i1.hdslb.com/bfs/face/c325ac5190623438323206a8bb720bc7ec4f6132.jpg","rank":"10000","DisplayRank":"0","face_nft_new":0,"is_senior_member":0,"level_info":{"current_level":6,"current_min":0,"current_exp":0,"next_exp":0},"pendant":{"pid":0,"name":"","image":"","expire":0,"image_enhance":"","image_enhance_frame":""},"nameplate":{"nid":74,"name":"大会员2018年度勋章","image":"http://i1.hdslb.com/bfs/face/421179426c929dfeaed4117461c83f5d07ffb148.png","image_small":"http://i2.hdslb.com/bfs/face/682001c2e1c2ae887bdf2a0e18eef61180c48f84.png","level":"稀有勋章","condition":"2018.6.26-7.8某一天是年度大会员"},"official_verify":{"type":-1,"desc":""},"vip":{"vipType":2,"vipDueDate":1698940800000,"dueRemark":"","accessStatus":0,"vipStatus":1,"vipStatusWarn":"","themeType":0,"label":{"path":"","text":"年度大会员","label_theme":"annual_vip","text_color":"#FFFFFF","bg_style":1,"bg_color":"#FB7299","border_color":""},"avatar_subscript":1,"avatar_subscript_url":"http://i0.hdslb.com/bfs/vip/icon_Certification_big_member_22_3x.png","nickname_color":"#FB7299"},"fans_detail":null,"following":0,"is_followed":0,"user_sailing":{"pendant":null,"cardbg":null,"cardbg_with_focus":null},"is_contractor":false,"contract_desc":""},"content":{"message":"打倒！","plat":0,"device":"","members":[],"jump_url":{},"max_line":6},"replies":null,"assist":0,"folder":{"has_folded":false,"is_folded":false,"rule":"https://www.bilibili.com/blackboard/foldingreply.html"},"up_action":{"like":false,"reply":false},"show_follow":false,"invisible":false,"reply_control":{"time_desc":"1099天前发布"}},{"rpid":1301616056,"oid":1858957,"type":12,"mid":33701413,"root":0,"parent":0,"dialog":0,"count":0,"rcount":0,"state":0,"fansgrade":0,"attr":0,"ctime":1547383911,"rpid_str":"1301616056","root_str":"0","parent_str":"0","like":0,"action":0,"member":{"mid":"33701413","uname":"黑岩今天出手游了吗","sex":"男","sign":"为什么百合控这么苦啊ヾ(。￣□￣)ツ","avatar":"http://i1.hdslb.com/bfs/face/ba6dda7dffcd92589ce134605905c210d2c227c7.jpg","rank":"10000","DisplayRank":"0","face_nft_new":0,"is_senior_member":0,"level_info":{"current_level":6,"current_min":0,"current_exp":0,"next_exp":0},"pendant":{"pid":0,"name":"","image":"","expire":0,"image_enhance":"","image_enhance_frame":""},"nameplate":{"nid":62,"name":"有爱大佬","image":"http://i1.hdslb.com/bfs/face/a10ee6b613e0d68d2dfdac8bbf71b94824e10408.png","image_small":"http://i1.hdslb.com/bfs/face/54f4c31ab9b1f1fa2c29dbbc967f66535699337e.png","level":"普通勋章","condition":"当前持有粉丝勋章最高等级>=15级"},"official_verify":{"type":-1,"desc":""},"vip":{"vipType":1,"vipDueDate":1634745600000,"dueRemark":"","accessStatus":0,"vipStatus":0,"vipStatusWarn":"","themeType":0,"label":{"path":"","text":"","label_theme":"","text_color":"","bg_style":0,"bg_color":"","border_color":""},"avatar_subscript":0,"nickname_color":""},"fans_detail":null,"following":0,"is_followed":0,"user_sailing":{"pendant":null,"cardbg":null,"cardbg_with_focus":null},"is_contractor":false,"contract_desc":""},"content":{"message":"露妈妈操碎了心","plat":0,"device":"","members":[],"jump_url":{},"max_line":6},"replies":null,"assist":0,"folder":{"has_folded":false,"is_folded":false,"rule":"https://www.bilibili.com/blackboard/foldingreply.html"},"up_action":{"like":false,"reply":false},"show_follow":false,"invisible":false,"reply_control":{"time_desc":"1099天前发布"}},{"rpid":1301503609,"oid":1858957,"type":12,"mid":67143160,"root":0,"parent":0,"dialog":0,"count":0,"rcount":0,"state":0,"fansgrade":0,"attr":0,"ctime":1547381032,"rpid_str":"1301503609","root_str":"0","parent_str":"0","like":0,"action":0,"member":{"mid":"67143160","uname":"南條むしん","sex":"保密","sign":"京蜜，声优厨，单推南条爱乃，高桥李依等等。\nnano可爱！","avatar":"http://i1.hdslb.com/bfs/face/36acf37f297d0ac2c9d43e9ba25fed2fa77ff2dc.jpg","rank":"10000","DisplayRank":"0","face_nft_new":0,"is_senior_member":0,"level_info":{"current_level":6,"current_min":0,"current_exp":0,"next_exp":0},"pendant":{"pid":4724,"name":"椎名菜羽","image":"http://i1.hdslb.com/bfs/garb/item/255d1a576b06986a08ffbf37682b3033cd37a075.png","expire":0,"image_enhance":"http://i1.hdslb.com/bfs/garb/item/255d1a576b06986a08ffbf37682b3033cd37a075.png","image_enhance_frame":""},"nameplate":{"nid":62,"name":"有爱大佬","image":"http://i2.hdslb.com/bfs/face/a10ee6b613e0d68d2dfdac8bbf71b94824e10408.png","image_small":"http://i1.hdslb.com/bfs/face/54f4c31ab9b1f1fa2c29dbbc967f66535699337e.png","level":"普通勋章","condition":"当前持有粉丝勋章最高等级>=15级"},"official_verify":{"type":-1,"desc":""},"vip":{"vipType":2,"vipDueDate":1680364800000,"dueRemark":"","accessStatus":0,"vipStatus":1,"vipStatusWarn":"","themeType":0,"label":{"path":"","text":"年度大会员","label_theme":"annual_vip","text_color":"#FFFFFF","bg_style":1,"bg_color":"#FB7299","border_color":""},"avatar_subscript":1,"avatar_subscript_url":"http://i0.hdslb.com/bfs/vip/icon_Certification_big_member_22_3x.png","nickname_color":"#FB7299"},"fans_detail":null,"following":0,"is_followed":0,"user_sailing":{"pendant":{"id":4724,"name":"椎名菜羽","image":"http://i0.hdslb.com/bfs/garb/item/255d1a576b06986a08ffbf37682b3033cd37a075.png","jump_url":"","type":"suit","image_enhance":"http://i0.hdslb.com/bfs/garb/item/255d1a576b06986a08ffbf37682b3033cd37a075.png","image_enhance_frame":""},"cardbg":{"id":4745,"name":"椎名菜羽","image":"http://i0.hdslb.com/bfs/garb/item/a9f749ab74131da9d7011ec62186959a61f245a7.png","jump_url":"https://www.bilibili.com/h5/mall/fans/recommend/4749?navhide=1&mid=67143160&from=reply","fan":{"is_fan":1,"number":2787,"color":"#f4a75c","name":"椎名菜羽","num_desc":"002787"},"type":"suit"},"cardbg_with_focus":null},"is_contractor":false,"contract_desc":""},"content":{"message":"不愧是团宠阿光","plat":0,"device":"","members":[],"jump_url":{},"max_line":6},"replies":null,"assist":0,"folder":{"has_folded":false,"is_folded":false,"rule":"https://www.bilibili.com/blackboard/foldingreply.html"},"up_action":{"like":false,"reply":false},"show_follow":false,"invisible":false,"reply_control":{"time_desc":"1099天前发布"}},{"rpid":1301193021,"oid":1858957,"type":12,"mid":3283194,"root":0,"parent":0,"dialog":0,"count":0,"rcount":0,"state":0,"fansgrade":0,"attr":0,"ctime":1547372412,"rpid_str":"1301193021","root_str":"0","parent_str":"0","like":0,"action":0,"member":{"mid":"3283194","uname":"映天海primula","sex":"保密","sign":"明日お嫌っで　過去に願っで","avatar":"http://i0.hdslb.com/bfs/face/5a85b9aa24446c5d464839699cecebe4cc89ce6b.jpg","rank":"10000","DisplayRank":"0","face_nft_new":0,"is_senior_member":0,"level_info":{"current_level":6,"current_min":0,"current_exp":0,"next_exp":0},"pendant":{"pid":0,"name":"","image":"","expire":0,"image_enhance":"","image_enhance_frame":""},"nameplate":{"nid":0,"name":"","image":"","image_small":"","level":"","condition":""},"official_verify":{"type":-1,"desc":""},"vip":{"vipType":1,"vipDueDate":1642867200000,"dueRemark":"","accessStatus":0,"vipStatus":1,"vipStatusWarn":"","themeType":0,"label":{"path":"","text":"大会员","label_theme":"vip","text_color":"#FFFFFF","bg_style":1,"bg_color":"#FB7299","border_color":""},"avatar_subscript":1,"avatar_subscript_url":"http://i0.hdslb.com/bfs/vip/icon_Certification_big_member_22_3x.png","nickname_color":""},"fans_detail":null,"following":0,"is_followed":0,"user_sailing":{"pendant":null,"cardbg":null,"cardbg_with_focus":null},"is_contractor":false,"contract_desc":""},"content":{"message":"闪耀增加了笑死 多出来的这些重量...到底...[小电视_笑]","plat":0,"device":"","members":[],"emote":{"[小电视_笑]":{"id":121,"package_id":5,"state":0,"type":2,"attr":0,"text":"[小电视_笑]","url":"http://i0.hdslb.com/bfs/emote/f80d384875183dfe2e24be13011c595c0210d273.png","meta":{"size":2},"mtime":1628587688,"jump_title":"笑"}},"jump_url":{},"max_line":6},"replies":null,"assist":0,"folder":{"has_folded":false,"is_folded":false,"rule":"https://www.bilibili.com/blackboard/foldingreply.html"},"up_action":{"like":false,"reply":false},"show_follow":false,"invisible":false,"reply_control":{"time_desc":"1099天前发布"}},{"rpid":1301169527,"oid":1858957,"type":12,"mid":347414,"root":0,"parent":0,"dialog":0,"count":0,"rcount":0,"state":0,"fansgrade":0,"attr":0,"ctime":1547371894,"rpid_str":"1301169527","root_str":"0","parent_str":"0","like":0,"action":0,"member":{"mid":"347414","uname":"フジヤマディスコ","sex":"女","sign":"","avatar":"http://i2.hdslb.com/bfs/face/41b2518cb6adacf9c81574b25ed6958a708ce7b2.jpg","rank":"10000","DisplayRank":"0","face_nft_new":0,"is_senior_member":0,"level_info":{"current_level":6,"current_min":0,"current_exp":0,"next_exp":0},"pendant":{"pid":0,"name":"","image":"","expire":0,"image_enhance":"","image_enhance_frame":""},"nameplate":{"nid":0,"name":"","image":"","image_small":"","level":"","condition":""},"official_verify":{"type":-1,"desc":""},"vip":{"vipType":2,"vipDueDate":1672243200000,"dueRemark":"","accessStatus":0,"vipStatus":1,"vipStatusWarn":"","themeType":0,"label":{"path":"","text":"年度大会员","label_theme":"annual_vip","text_color":"#FFFFFF","bg_style":1,"bg_color":"#FB7299","border_color":""},"avatar_subscript":1,"avatar_subscript_url":"http://i0.hdslb.com/bfs/vip/icon_Certification_big_member_22_3x.png","nickname_color":"#FB7299"},"fans_detail":null,"following":0,"is_followed":0,"user_sailing":{"pendant":null,"cardbg":null,"cardbg_with_focus":null},"is_contractor":false,"contract_desc":""},"content":{"message":"小光真的太可爱了awsl","plat":0,"device":"","members":[],"jump_url":{},"max_line":6},"replies":null,"assist":0,"folder":{"has_folded":false,"is_folded":false,"rule":"https://www.bilibili.com/blackboard/foldingreply.html"},"up_action":{"like":false,"reply":false},"show_follow":false,"invisible":false,"reply_control":{"time_desc":"1099天前发布"}},{"rpid":1301010460,"oid":1858957,"type":12,"mid":281378616,"root":0,"parent":0,"dialog":0,"count":0,"rcount":0,"state":0,"fansgrade":0,"attr":0,"ctime":1547367255,"rpid_str":"1301010460","root_str":"0","parent_str":"0","like":0,"action":0,"member":{"mid":"281378616","uname":"嗶嗶0110","sex":"保密","sign":"","avatar":"http://i0.hdslb.com/bfs/face/f22001df5c14b29565c82a460533f26f53ceb34f.jpg","rank":"10000","DisplayRank":"0","face_nft_new":0,"is_senior_member":0,"level_info":{"current_level":5,"current_min":0,"current_exp":0,"next_exp":0},"pendant":{"pid":0,"name":"","image":"","expire":0,"image_enhance":"","image_enhance_frame":""},"nameplate":{"nid":0,"name":"","image":"","image_small":"","level":"","condition":""},"official_verify":{"type":-1,"desc":""},"vip":{"vipType":0,"vipDueDate":0,"dueRemark":"","accessStatus":0,"vipStatus":0,"vipStatusWarn":"","themeType":0,"label":{"path":"","text":"","label_theme":"","text_color":"","bg_style":0,"bg_color":"","border_color":""},"avatar_subscript":0,"nickname_color":""},"fans_detail":null,"following":0,"is_followed":0,"user_sailing":{"pendant":null,"cardbg":null,"cardbg_with_focus":null},"is_contractor":false,"contract_desc":""},"content":{"message":"光好可愛","plat":0,"device":"","members":[],"jump_url":{},"max_line":6},"replies":null,"assist":0,"folder":{"has_folded":false,"is_folded":false,"rule":"https://www.bilibili.com/blackboard/foldingreply.html"},"up_action":{"like":false,"reply":false},"show_follow":false,"invisible":false,"reply_control":{"time_desc":"1099天前发布"}},{"rpid":1300551804,"oid":1858957,"type":12,"mid":1909536,"root":0,"parent":0,"dialog":0,"count":0,"rcount":0,"state":0,"fansgrade":0,"attr":0,"ctime":1547354765,"rpid_str":"1300551804","root_str":"0","parent_str":"0","like":0,"action":0,"member":{"mid":"1909536","uname":"调查员Pan","sex":"男","sign":"骑砍、东方、中V、冷兵器、克苏鲁、铁血战士爱好者。","avatar":"http://i0.hdslb.com/bfs/face/73fc3db37571241c2b363d2c3e0a3d1c9a6a04ae.jpg","rank":"10000","DisplayRank":"0","face_nft_new":0,"is_senior_member":0,"level_info":{"current_level":6,"current_min":0,"current_exp":0,"next_exp":0},"pendant":{"pid":0,"name":"","image":"","expire":0,"image_enhance":"","image_enhance_frame":""},"nameplate":{"nid":0,"name":"","image":"","image_small":"","level":"","condition":""},"official_verify":{"type":-1,"desc":""},"vip":{"vipType":2,"vipDueDate":1652371200000,"dueRemark":"","accessStatus":0,"vipStatus":1,"vipStatusWarn":"","themeType":0,"label":{"path":"","text":"年度大会员","label_theme":"annual_vip","text_color":"#FFFFFF","bg_style":1,"bg_color":"#FB7299","border_color":""},"avatar_subscript":1,"avatar_subscript_url":"http://i0.hdslb.com/bfs/vip/icon_Certification_big_member_22_3x.png","nickname_color":"#FB7299"},"fans_detail":null,"following":0,"is_followed":0,"user_sailing":{"pendant":null,"cardbg":null,"cardbg_with_focus":null},"is_contractor":false,"contract_desc":""},"content":{"message":"抹布洗！","plat":0,"device":"","members":[],"jump_url":{},"max_line":6},"replies":null,"assist":0,"folder":{"has_folded":false,"is_folded":false,"rule":"https://www.bilibili.com/blackboard/foldingreply.html"},"up_action":{"like":false,"reply":false},"show_follow":false,"invisible":false,"reply_control":{"time_desc":"1099天前发布"}},{"rpid":1300441345,"oid":1858957,"type":12,"mid":3793947,"root":0,"parent":0,"dialog":0,"count":0,"rcount":0,"state":0,"fansgrade":0,"attr":0,"ctime":1547352015,"rpid_str":"1300441345","root_str":"0","parent_str":"0","like":0,"action":0,"member":{"mid":"3793947","uname":"A7M2阿尔法","sex":"保密","sign":"","avatar":"http://i0.hdslb.com/bfs/face/e4f3e2a696a5f1bbee244f693c8ca888cd04719f.jpg","rank":"10000","DisplayRank":"0","face_nft_new":0,"is_senior_member":0,"level_info":{"current_level":6,"current_min":0,"current_exp":0,"next_exp":0},"pendant":{"pid":0,"name":"","image":"","expire":0,"image_enhance":"","image_enhance_frame":""},"nameplate":{"nid":0,"name":"","image":"","image_small":"","level":"","condition":""},"official_verify":{"type":-1,"desc":""},"vip":{"vipType":2,"vipDueDate":1649174400000,"dueRemark":"","accessStatus":0,"vipStatus":1,"vipStatusWarn":"","themeType":0,"label":{"path":"","text":"年度大会员","label_theme":"annual_vip","text_color":"#FFFFFF","bg_style":1,"bg_color":"#FB7299","border_color":""},"avatar_subscript":1,"avatar_subscript_url":"http://i0.hdslb.com/bfs/vip/icon_Certification_big_member_22_3x.png","nickname_color":"#FB7299"},"fans_detail":null,"following":0,"is_followed":0,"user_sailing":{"pendant":null,"cardbg":null,"cardbg_with_focus":null},"is_contractor":false,"contract_desc":""},"content":{"message":"露妈妈操碎了心","plat":0,"device":"","members":[],"jump_url":{},"max_line":6},"replies":null,"assist":0,"folder":{"has_folded":false,"is_folded":false,"rule":"https://www.bilibili.com/blackboard/foldingreply.html"},"up_action":{"like":false,"reply":false},"show_follow":false,"invisible":false,"reply_control":{"time_desc":"1099天前发布"}}],"top":{"admin":null,"upper":null,"vote":null},"top_replies":null,"lottery_card":null,"folder":{"has_folded":false,"is_folded":false,"rule":"https://www.bilibili.com/blackboard/foldingreply.html"},"up_selection":{"pending_count":0,"ignore_count":0},"cm":{},"effects":{"preloading":""},"assist":0,"blacklist":0,"vote":0,"lottery":0,"config":{"showadmin":1,"showentry":1,"showfloor":0,"showtopic":0,"show_up_flag":false,"read_only":false,"show_del_log":true},"upper":{"mid":234441166},"show_bvid":false,"control":{"input_disable":false,"root_input_text":"发一条友善的评论","child_input_text":"","giveup_input_text":"不发没关系，请继续友善哦~","bg_text":"看看下面~来发评论吧","web_selection":false,"answer_guide_text":"需要升级成为lv2会员后才可以评论，先去答题转正吧！","answer_guide_icon_url":"http://i0.hdslb.com/bfs/emote/96940d16602cacbbac796245b7bb99fa9b5c970c.png","answer_guide_ios_url":"https://www.bilibili.com/h5/newbie/entry?navhide=1&re_src=12","answer_guide_android_url":"https://www.bilibili.com/h5/newbie/entry?navhide=1&re_src=6","show_type":1,"show_text":"","disable_jump_emote":false},"note":0,"callbacks":null}}